CHANGELOG.txt
LICENSE.txt
MANIFEST.in
README.txt
ez_setup.py
setup.cfg
setup.py
CommandTool.egg-info/PKG-INFO
CommandTool.egg-info/SOURCES.txt
CommandTool.egg-info/dependency_links.txt
CommandTool.egg-info/entry_points.txt
CommandTool.egg-info/not-zip-safe
CommandTool.egg-info/requires.txt
CommandTool.egg-info/top_level.txt
commandtool/__init__.py
commandtool/recipes_267662.py
doc/Makefile
doc/index.txt
doc/source/NEW.txt
doc/source/api.rst
doc/source/conf.py
doc/source/index.rst
doc/source/manual.rst
example/find/find.py
example/find/test.html
test/README.txt
test/doc.py