Metadata-Version: 1.0
Name: CommandTool
Version: 0.5.3
Summary: Tools for creating command line interfaces involving sub-commands.
Home-page: http://jimmyg.org/work/code/commandtool/index.html
Author: James Gardner
Author-email: UNKNOWN
License: MIT
Platform: UNKNOWN
Classifier: Development Status :: 3 - Alpha
Classifier: License :: OSI Approved :: MIT License
Classifier: Programming Language :: Python :: 2
Classifier: Topic :: Software Development :: Libraries :: Python Modules
Classifier: Environment :: Console
